metatags/__init__.py
metatags/admin.py
metatags/apps.py
metatags/models.py
metatags/tests.py
metatags/views.py
metatags/migrations/0001_initial.py
metatags/migrations/__init__.py
metatags/templatetags/__init__.py
metatags/templatetags/metatags.py
django_easy_metatags-0.2.dist-info/LICENSE.txt
django_easy_metatags-0.2.dist-info/METADATA
django_easy_metatags-0.2.dist-info/WHEEL
django_easy_metatags-0.2.dist-info/top_level.txt
django_easy_metatags-0.2.dist-info/RECORD
