Metadata-Version: 2.1
Name: django-easy-metatags
Version: 0.2
Summary: A Django app to add meta tags to any page of your website.
Home-page: https://github.com/Hardeepsingh980/django_simple_metatags
Author: Hardeep Singh
Author-email: hardeep0khalsa122@gmail.com
License: MIT License  # Example license
Platform: UNKNOWN
Classifier: Programming Language :: Python :: 3
Classifier: License :: OSI Approved :: MIT License
Classifier: Operating System :: OS Independent
Requires-Python: >=3.6
